uplooking/__init__.py
uplooking/uplookingjson.py
uplooking-0.1.0.dist-info/LICENSE.lic
uplooking-0.1.0.dist-info/METADATA
uplooking-0.1.0.dist-info/WHEEL
uplooking-0.1.0.dist-info/top_level.txt
uplooking-0.1.0.dist-info/RECORD
